setup.cfg
setup.py
Flask_SAPB1.egg-info/PKG-INFO
Flask_SAPB1.egg-info/SOURCES.txt
Flask_SAPB1.egg-info/dependency_links.txt
Flask_SAPB1.egg-info/not-zip-safe
Flask_SAPB1.egg-info/requires.txt
Flask_SAPB1.egg-info/top_level.txt
flask_sapb1/SAPbobsCOM2005.py
flask_sapb1/SAPbobsCOM2007.py
flask_sapb1/SAPbobsCOM67.py
flask_sapb1/SAPbobsCOM88.py
flask_sapb1/SAPbobsCOM89.py
flask_sapb1/SAPbobsCOM90.py
flask_sapb1/__init__.py
flask_sapb1/flask_sapb1.py